sealpy3/__init__.py
sealpy3/cmdline.py
sealpy3/log.py
sealpy3/seal_py.py
sealpy3-0.1.6.dist-info/METADATA
sealpy3-0.1.6.dist-info/WHEEL
sealpy3-0.1.6.dist-info/entry_points.txt
sealpy3-0.1.6.dist-info/RECORD
