Metadata-Version: 2.1
Name: sealpy3
Version: 0.1.6
Summary: seal your pyfiles or project by using cythonize.
Home-page: https://github.com/limoncc/sealpy
License: MIT
Author: limoncc
Author-email: limoncc@icloud.com
Requires-Python: >=3.8,<4
Classifier: License :: OSI Approved :: MIT License
Classifier: Programming Language :: Python :: 3
Classifier: Programming Language :: Python :: 3.8
Classifier: Programming Language :: Python :: 3.9
Classifier: Programming Language :: Python :: 3.10
Classifier: Programming Language :: Python :: 3.11
Classifier: Programming Language :: Python :: 3.12
Requires-Dist: cython (>=3.0.11,<4.0.0)
Project-URL: Repository, https://github.com/limoncc/sealpy
